[
    {
        "id": "c5ceaf7c7ef94375bfec88e0818ff1cb",
        "platform": "CodeChef",
        "title": "Weekend Dev Challenge 39: Spring Boot Projects",
        "url": "https://www.codechef.com/DEVWEEKEND39",
        "start_time": "2026-02-28T00:00:00+05:30",
        "duration": 172800
    },
    {
        "id": "85565f0a7be34241a1f328d5dbcd83c1",
        "platform": "CodeChef",
        "title": "Monday Munch - DSA Challenge 27",
        "url": "https://www.codechef.com/DSAMONDAY27",
        "start_time": "2026-03-02T18:00:00+05:30",
        "duration": 10800
    },
    {
        "id": "1dcb43139c2d4acfba3dbace7f791770",
        "platform": "CodeChef",
        "title": "Starters 228",
        "url": "https://www.codechef.com/START228",
        "start_time": "2026-03-04T20:00:00+05:30",
        "duration": 7200
    },
    {
        "id": "732d77fb81f24440bcb71fefb5bee292",
        "platform": "CodeChef",
        "title": "Monday Munch - DSA Challenge 28",
        "url": "https://www.codechef.com/DSAMONDAY28",
        "start_time": "2026-03-09T18:00:00+05:30",
        "duration": 10800
    },
    {
        "id": "5bca0c26d008453ba400183546e425ff",
        "platform": "CodeChef",
        "title": "Starters 229",
        "url": "https://www.codechef.com/START229",
        "start_time": "2026-03-11T20:00:00+05:30",
        "duration": 7200
    },
    {
        "id": "a208390f0d9940db8371e9f82fd30d59",
        "platform": "Codeforces",
        "title": "Educational Codeforces Round 188 (Rated for Div. 2)",
        "url": "https://codeforces.com/contests/2204",
        "start_time": "2026-03-16T20:05:00+05:30",
        "duration": 7200
    },
    {
        "id": "2b597eb0174746d1be6b26184ed8b57a",
        "platform": "Codeforces",
        "title": "Codeforces Round (Div. 1 + Div. 2)",
        "url": "https://codeforces.com/contests/2207",
        "start_time": "2026-03-08T20:05:00+05:30",
        "duration": 10800
    },
    {
        "id": "4060cfbe52ba4cd49f1c2431db5cf2b9",
        "platform": "Codeforces",
        "title": "2026 ICPC Asia Pacific Championship - Online Mirror (Unrated, Online Mirror, ICPC Rules, Teams Preferred)",
        "url": "https://codeforces.com/contests/2206",
        "start_time": "2026-03-08T07:15:00+05:30",
        "duration": 18000
    },
    {
        "id": "a932281cf5f145c3959cd869b3302abf",
        "platform": "Codeforces",
        "title": "Kotlin Heroes: Episode 14",
        "url": "https://codeforces.com/contests/2199",
        "start_time": "2026-03-02T20:05:00+05:30",
        "duration": 9000
    },
    {
        "id": "5c1b99259af5484688a6f8ede596bce8",
        "platform": "Codeforces",
        "title": "Codeforces Round 1084 (Div. 3)",
        "url": "https://codeforces.com/contests/2200",
        "start_time": "2026-02-27T20:05:00+05:30",
        "duration": 8100
    },
    {
        "id": "3f1be29492094088b11cf28d77877bc6",
        "platform": "Codeforces",
        "title": "Kotlin Heroes: Practice 14",
        "url": "https://codeforces.com/contests/2198",
        "start_time": "2026-02-21T20:00:00+05:30",
        "duration": 777600
    },
    {
        "id": "1fcf1ee8a81a494ca64e2000aacd96c6",
        "platform": "LeetCode",
        "title": "Biweekly Contest 178",
        "url": "https://leetcode.com/contest/biweekly-contest-178",
        "start_time": "2026-03-14T20:00:00+05:30",
        "duration": 5400
    },
    {
        "id": "430dd88b5a6a43dea096674889709b97",
        "platform": "LeetCode",
        "title": "Weekly Contest 492",
        "url": "https://leetcode.com/contest/weekly-contest-492",
        "start_time": "2026-03-08T08:00:00+05:30",
        "duration": 5400
    },
    {
        "id": "6d60b0a13ad149048a9479e061fc5937",
        "platform": "LeetCode",
        "title": "Weekly Contest 491",
        "url": "https://leetcode.com/contest/weekly-contest-491",
        "start_time": "2026-03-01T08:00:00+05:30",
        "duration": 5400
    },
    {
        "id": "c209fd25c82e49a2b9ca563b0d287fa0",
        "platform": "LeetCode",
        "title": "Biweekly Contest 177",
        "url": "https://leetcode.com/contest/biweekly-contest-177",
        "start_time": "2026-02-28T20:00:00+05:30",
        "duration": 5400
    },
    {
        "id": "5f9ea5bd09544bad8e3b26c0ebe77bef",
        "platform": "AtCoder",
        "title": "AtCoder Beginner Contest 447",
        "url": "https://atcoder.jp/contests/abc447",
        "start_time": "2026-02-28T21:00:00+09:00",
        "duration": 6000
    },
    {
        "id": "413ae0803d75441085d1d1105676f39f",
        "platform": "AtCoder",
        "title": "The 3rd Masters Championship-qual-",
        "url": "https://atcoder.jp/contests/masters2026-qual",
        "start_time": "2026-03-01T13:00:00+09:00",
        "duration": 21600
    },
    {
        "id": "2ac746db73fe4d88ac20140adb60b911",
        "platform": "AtCoder",
        "title": "AtCoder Beginner Contest 448",
        "url": "https://atcoder.jp/contests/abc448",
        "start_time": "2026-03-07T21:00:00+09:00",
        "duration": 6000
    },
    {
        "id": "1337f26ebf6849c08f0d069f5b5fce60",
        "platform": "AtCoder",
        "title": "UNIQUE VISION Programming Contest 2026 Spring (AtCoder Heuristic Contest 062)",
        "url": "https://atcoder.jp/contests/ahc062",
        "start_time": "2026-03-14T15:00:00+09:00",
        "duration": 14400
    },
    {
        "id": "649ee70e73c94c32ac10c1952d98cc79",
        "platform": "AtCoder",
        "title": "AtCoder Beginner Contest 449",
        "url": "https://atcoder.jp/contests/abc449",
        "start_time": "2026-03-14T21:00:00+09:00",
        "duration": 6000
    },
    {
        "id": "1e496ceafb0b48168cfef07251cbb46b",
        "platform": "AtCoder",
        "title": "AtCoder Beginner Contest 450",
        "url": "https://atcoder.jp/contests/abc450",
        "start_time": "2026-03-21T21:00:00+09:00",
        "duration": 6000
    },
    {
        "id": "aad7a27e70f947b79de6232e2f5ccfe4",
        "platform": "AtCoder",
        "title": "AtCoder Grand Contest 077",
        "url": "https://atcoder.jp/contests/agc077",
        "start_time": "2026-03-29T21:00:00+09:00",
        "duration": 10800
    }
]